{
  "name"    : "node_outputLOG",
  "type"    : "outputs",
  "table"   : 0,
  "heading" : "Журнал",
  "short"   : "LOG",
  "help"    : "Записать пользовательское событие в журнал. По переднему фронту (переход с false на true) происходит запись строки на входе в журнал устройства.",
  "compiler" : {
    "denisScript" : null
  },
  "options" : [],
  "inputs"  : [
    {
      "type"   : "string",
      "help"   : "Запись журнала"
    },{
      "type"   : "bool",
      "help"   : "Записать"
    }
  ],
  "outputs" : []
}
